Metadata-Version: 2.1
Name: configrator
Version: 0.0.1
Summary: A package to manage config files
Author: ZribeDev
Author-email: zribedev.manager@gmail.com
